{
  "project_info": {
    "project_number": "825268150118",
    "firebase_url": "https://sa-project-ab99f.firebaseio.com",
    "project_id": "sa-project-ab99f",
    "storage_bucket": "sa-project-ab99f.appspot.com"
  },
  "client": [
    {
      "client_info": {
        "mobilesdk_app_id": "1:825268150118:android:8df9c6cc235a618f",
        "android_client_info": {
          "package_name": "com.example.satest"
        }
      },
      "oauth_client": [
        {
          "client_id": "825268150118-or5uqeg7brj873f07jk9m1o7rm490j8p.apps.googleusercontent.com",
          "client_type": 3
        }
      ],
      "api_key": [
        {
          "current_key": "AIzaSyAHB0DpR1TC6ErlDD1PjaAxn4Lz54BCOTs"
        }
      ],
      "services": {
        "appinvite_service": {
          "other_platform_oauth_client": [
            {
              "client_id": "825268150118-or5uqeg7brj873f07jk9m1o7rm490j8p.apps.googleusercontent.com",
              "client_type": 3
            }
          ]
        }
      }
    }
  ],
  "configuration_version": "1"
}